roo_conf/__init__.py
roo_conf/deploy.py
roo_conf/py.typed
roo_conf/settings_manager.py
roo_conf/prompts/system-prompt-architect-gh.md
roo_conf/prompts/system-prompt-code-gh.md
roo_conf-0.1.13.dist-info/METADATA
roo_conf-0.1.13.dist-info/WHEEL
roo_conf-0.1.13.dist-info/entry_points.txt
roo_conf-0.1.13.dist-info/RECORD
