Metadata-Version: 2.4
Name: roo-conf
Version: 0.1.13
Summary: A configuration and prompt updater for Roo Code
Author-email: Mark Stouffer <1802850+InTEGr8or@users.noreply.github.com>
Requires-Python: >=3.12
